numcertain-0.3.0.dist-info/LICENSE
numcertain-0.3.0.dist-info/top_level.txt
numcertain-0.3.0.dist-info/WHEEL
numcertain-0.3.0.dist-info/RECORD
numcertain-0.3.0.dist-info/METADATA
numcertain/_numcertain.cpython-39-x86_64-linux-gnu.so
numcertain/_version.py
numcertain/__init__.py
