Metadata-Version: 2.1
Name: numcertain
Version: 0.3.0
Summary: A python & numpy data type for floating point numbers with quantified uncertainity.
Author-email: Garry O'Donnell <garry.o'donnell@diamond.ac.uk>
Maintainer-email: Garry O'Donnell <garry.o'donnell@diamond.ac.uk>
License:                                  Apache License
Project-URL: GitHub, https://github.com/DiamondLightSource/numcertain
Classifier: Development Status :: 4 - Beta
Classifier: License :: OSI Approved :: Apache Software License
Classifier: Programming Language :: Python :: 3.9
Classifier: Programming Language :: Python :: 3.10
Requires-Python: >=3.9
Provides-Extra: dev
Provides-Extra: docs
License-File: LICENSE
